.coveragerc
.testr.conf
AUTHORS
ChangeLog
LICENSE
MANIFEST.in
README.rst
requirements.txt
setup.cfg
setup.py
test-requirements.txt
tox.ini
rejviz/__init__.py
rejviz/libvirt_nets.py
rejviz/nic.py
rejviz/nic_mappings.py
rejviz/tmp.py
rejviz/utils.py
rejviz.egg-info/PKG-INFO
rejviz.egg-info/SOURCES.txt
rejviz.egg-info/dependency_links.txt
rejviz.egg-info/entry_points.txt
rejviz.egg-info/not-zip-safe
rejviz.egg-info/requires.txt
rejviz.egg-info/top_level.txt
rejviz/cmd/__init__.py
rejviz/cmd/builder.py
rejviz/cmd/install.py
rejviz/templates/fetch_nic.guestfish.j2
rejviz/templates/ifcfg-eth.j2
rejviz/tests/__init__.py
rejviz/tests/test_libvirt_nets.py
rejviz/tests/test_nic.py
rejviz/tests/test_nic_mappings.py
rejviz/tests/test_tmp.py
rejviz/tests/test_utils.py
rejviz/tests/utils.py
rejviz/tests/cmd/__init__.py
rejviz/tests/cmd/test_builder.py
rejviz/tests/cmd/test_install.py