Metadata-Version: 1.1
Name: rejviz
Version: 0.0.1
Summary: Additional features on top of libguestfs-tools
Home-page: https://github.com/jistr/rejviz
Author: Jiri Stransky
Author-email: jistr@redhat.com
License: Apache License, Version 2.0
Platform: UNKNOWN
Classifier: Environment :: Console
Classifier: Intended Audience :: Developers
Classifier: Intended Audience :: Information Technology
Classifier: License :: OSI Approved :: Apache Software License
Classifier: Operating System :: POSIX
Classifier: Programming Language :: Python
Classifier: Programming Language :: Python :: 2
Classifier: Programming Language :: Python :: 2.7
Classifier: Programming Language :: Python :: 3
Classifier: Programming Language :: Python :: 3.3
